_pyconptyinternal.cp313-win_amd64.pyd
pyconpty/__init__.py
pyconpty/pyconpty.py
pyconpty-1.0.dist-info/licenses/LICENSE
pyconpty-1.0.dist-info/METADATA
pyconpty-1.0.dist-info/WHEEL
pyconpty-1.0.dist-info/top_level.txt
pyconpty-1.0.dist-info/RECORD
