Metadata-Version: 2.4
Name: pyconpty
Version: 1.0
Summary: A Python wrapper for the ConPTY (Windows Pseudo-console) API
Author-email: Melwyn Francis Carlo <melwyncarlo@gmail.com>
License-Expression: GPL-3.0-only
Project-URL: Homepage, https://github.com/melwyncarlo/PyConPTY
Project-URL: Issues, https://github.com/melwyncarlo/PyConPTY/issues
Keywords: pyconpty,conpty,windows,pseudo,console,pseudoconsole,winpty,pty,tty,terminal,subprocess
Classifier: Programming Language :: Python :: 3
Classifier: Operating System :: Microsoft :: Windows :: Windows 10
Classifier: Topic :: Software Development :: Libraries :: Python Modules
Classifier: Topic :: System :: Emulators
Classifier: Topic :: System :: Shells
Classifier: Topic :: Terminals :: Terminal Emulators/X Terminals
Classifier: Development Status :: 5 - Production/Stable
Classifier: Environment :: Console
Classifier: Natural Language :: English
Requires-Python: >=3.8
License-File: LICENSE
Dynamic: license-file
